my_node_selector/init.py
my_node_selector/main.py
my_node_selector-1.0.5.dist-info/METADATA
my_node_selector-1.0.5.dist-info/WHEEL
my_node_selector-1.0.5.dist-info/entry_points.txt
my_node_selector-1.0.5.dist-info/top_level.txt
my_node_selector-1.0.5.dist-info/RECORD
