Metadata-Version: 2.1
Name: my_node_selector
Version: 1.0.5
Requires-Dist: Pillow
